ewutils/__init__.py
ewutils/lists.py
ewutils/networking/__init__.py
ewutils/networking/http.py
ewutils/terminal/__init__.py
ewutils/terminal/curses.py
ewutils/terminal/linefmt.py
ewutils-1.0rc2.dist-info/DESCRIPTION.rst
ewutils-1.0rc2.dist-info/METADATA
ewutils-1.0rc2.dist-info/RECORD
ewutils-1.0rc2.dist-info/WHEEL
ewutils-1.0rc2.dist-info/metadata.json
ewutils-1.0rc2.dist-info/top_level.txt
