Metadata-Version: 2.0
Name: ewutils
Version: 1.0rc2
Summary: A collection of tools and utilities that I put together to make programming a little easier
Home-page: https://github.com/Ewpratten/ewutils
Author: Evan Pratten
Author-email: ewpratten@gmail.com
License: GPLv3
Platform: UNKNOWN
Classifier: Programming Language :: Python :: 3
Classifier: Operating System :: OS Independent
Classifier: Development Status :: 5 - Production/Stable
Requires-Dist: requests
